StringConverter/__init__.py
StringConverter/intStringConverter.py
StringConverter/test_code.py
StringConverter-0.0.1.dist-info/LICENSE
StringConverter-0.0.1.dist-info/METADATA
StringConverter-0.0.1.dist-info/WHEEL
StringConverter-0.0.1.dist-info/top_level.txt
StringConverter-0.0.1.dist-info/RECORD
