Metadata-Version: 2.1
Name: StringConverter
Version: 0.0.1
Summary: For generating PrettyStrings - currently support int only
Home-page: UNKNOWN
Author: Tamir Zecler
Author-email: tamir.zec@gmail.com
License: UNKNOWN
Platform: UNKNOWN
Classifier: Programming Language :: Python :: 3
Classifier: License :: OSI Approved :: MIT License
Classifier: Operating System :: OS Independent
License-File: LICENSE
